zplgen/__init__.py
zplgen/base.py
zplgen/utils.py
zplgen-0.0.5.dist-info/DESCRIPTION.rst
zplgen-0.0.5.dist-info/METADATA
zplgen-0.0.5.dist-info/RECORD
zplgen-0.0.5.dist-info/WHEEL
zplgen-0.0.5.dist-info/metadata.json
zplgen-0.0.5.dist-info/top_level.txt
