Metadata-Version: 2.0
Name: zplgen
Version: 0.0.5
Summary: A library to aid in generating ZPL2 code.
Home-page: https://github.com/kolonialno/zplgen
Author: Kolonial.no
Author-email: tech@kolonial.no
License: MIT
Keywords: zpl zpl2
Platform: UNKNOWN
Classifier: Development Status :: 4 - Beta
Classifier: Intended Audience :: Developers
Classifier: Intended Audience :: Manufacturing
Classifier: Topic :: Software Development :: Code Generators
Classifier: License :: OSI Approved :: MIT License
Classifier: Programming Language :: Python :: 2
Classifier: Programming Language :: Python :: 3
Requires-Dist: future
